AutoDataPreprocess/AutoDataPreprocess.py
AutoDataPreprocess/__init__.py
AutoDataPreprocess-0.1.4.dist-info/LICENSE
AutoDataPreprocess-0.1.4.dist-info/METADATA
AutoDataPreprocess-0.1.4.dist-info/WHEEL
AutoDataPreprocess-0.1.4.dist-info/top_level.txt
AutoDataPreprocess-0.1.4.dist-info/RECORD
