Metadata-Version: 2.1
Name: AutoDataPreprocess
Version: 0.1.4
Summary: A high-level library for automatic preprocessing of tabular data
Home-page: https://github.com/agirishkumar/AutoDataPreprocess
Author: Girish Kumar Adari
Author-email: adari.girishkumar@gmail.com
License: UNKNOWN
Platform: UNKNOWN
Classifier: Programming Language :: Python :: 3
Classifier: License :: OSI Approved :: MIT License
Classifier: Operating System :: OS Independent
Requires-Python: >=3.6
License-File: LICENSE
Requires-Dist: SQLAlchemy
Requires-Dist: category-encoders
Requires-Dist: imbalanced-learn
Requires-Dist: matplotlib
Requires-Dist: numpy
Requires-Dist: pandas
Requires-Dist: requests
Requires-Dist: scikit-learn
Requires-Dist: scipy
Requires-Dist: seaborn
Requires-Dist: statsmodels
Requires-Dist: umap-learn
Requires-Dist: ydata-profiling
